apiblueprint_view/__init__.py
apiblueprint_view/parser.py
apiblueprint_view/views.py
apiblueprint_view/draughtsman/__init__.py
apiblueprint_view/draughtsman/tests/__init__.py
apiblueprint_view/draughtsman/tests/test_draughtsman.py
apiblueprint_view/lib/libdrafter.so
apiblueprint_view/templates/api_docs/asset.html
apiblueprint_view/templates/api_docs/copy.html
apiblueprint_view/templates/api_docs/default_base.html
apiblueprint_view/templates/api_docs/docs_parent.html
apiblueprint_view/templates/api_docs/element.html
apiblueprint_view/templates/api_docs/request.html
apiblueprint_view/templates/api_docs/resource.html
apiblueprint_view/templates/api_docs/resource_group.html
apiblueprint_view/templates/api_docs/response.html
apiblueprint_view/templates/api_docs/transaction.html
apiblueprint_view/templates/api_docs/transition.html
apiblueprint_view/templatetags/__init__.py
apiblueprint_view/templatetags/dict_utils.py
django_apiblueprint_view-3.0.1.dist-info/METADATA
django_apiblueprint_view-3.0.1.dist-info/WHEEL
django_apiblueprint_view-3.0.1.dist-info/licenses/LICENSE
django_apiblueprint_view-3.0.1.dist-info/RECORD
