Metadata-Version: 2.4
Name: django-apiblueprint-view
Version: 3.0.1
Summary: Render API Blueprints on-the-fly using Django templates
License-Expression: MIT
License-File: LICENSE
Author: chris48s
Requires-Python: >=3.10
Classifier: Framework :: Django
Requires-Dist: Django (>=4.2)
Requires-Dist: cffi (>=2.0.0)
Requires-Dist: markdown2 (>=2.3.9)
Requires-Dist: refract (==0.4.0)
Project-URL: Home, https://github.com/chris48s/django-apiblueprint-view
Project-URL: Source, https://github.com/chris48s/django-apiblueprint-view
